{"69021":"BESSENAY","69022":"BIBOST","69028":"BRINDAS","69043":"CHAPONOST","69046":"CHARLY","69049":"CHASSELAY","69051":"CHAUSSAN","69057":"CHEVINAY","69059":"CIVRIEUX-D'AZERGUES","69067":"COURZIEU","69072":"DARDILLY","69076":"DOMMARTIN","69083":"EVEUX","69086":"FLEURIEUX-SUR-L'ARBRESLE","69091":"GIVORS","69094":"GREZIEU-LA-VARENNE","69096":"GRIGNY","69100":"IRIGNY","69112":"LENTILLY","69116":"LIMONEST","69117":"LISSIEU","69125":"MARCILLY-D'AZERGUES","69127":"MARCY-L'ETOILE","69131":"MESSIMY","69133":"MILLERY","69136":"MONTAGNY","69141":"MORNANT","69148":"ORLIENAS","69153":"POLEYMIEUX-AU-MONT-D'OR","69154":"POLLIONNAY","69171":"SAIN-BEL","69175":"SAVIGNY","69177":"SOURCIEUX-LES-MINES","69179":"BEAUVALLON","69190":"SAINTE-CONSORCE","69194":"SAINT-DIDIER-AU-MONT-D'OR","69200":"SAINT-FORGEUX","69207":"SAINT-GERMAIN-AU-MONT-D'OR","69216":"SAINT-JULIEN-SUR-BIBOST","69219":"SAINT-LAURENT-D'AGNY","69231":"SAINT-PIERRE-LA-PALUD","69236":"SAINT-ROMAIN-EN-GIER","69241":"TALUYERS","69249":"THURINS","69250":"LA TOUR-DE-SALVAGNY","69255":"VAUGNERAY","69260":"VERNAISON","69268":"VOURLES"}